{
  "color": {
    "text": {
      "default": {
        "value": "{color.grey.0}"
      },
      "subtle": {
        "value": "{color.grey.200}"
      },
      "error": {
        "value": "{color.red.400}"
      },
      "disabled": {
        "value": "{color.grey.100}"
      },
      "success": {
        "value": "{color.green.400}"
      },
      "brand": {
        "primary": {
          "default": {
            "value": "{color.pink.300}"
          },
          "hover": {
            "value": "{color.pink.400}"
          }
        },
        "secondary": {
          "default": {
            "value": "{color.purple.300}"
          },
          "hover": {
            "value": "{color.purple.400}"
          }
        }
      },
      "inverted": {
        "value": "{color.grey.500}"
      },
      "locked": {
        "value": "{color.grey.0}"
      }
    },
    "border": {
      "default": {
        "value": "{color.grey.200}"
      },
      "subtle": {
        "value": "{color.grey.300}"
      },
      "disabled": {
        "value": "{color.grey.300}"
      },
      "error": {
        "value": "{color.red.400}"
      },
      "focused": {
        "value": "{color.grey.0}"
      },
      "brand": {
        "primary": {
          "default": {
            "value": "{color.pink.300}"
          },
          "hover": {
            "value": "{color.pink.400}"
          }
        }
      },
      "selected": {
        "value": "{color.grey.0}"
      }
    },
    "background": {
      "default": {
        "value": "{color.grey.500}"
      },
      "subtle": {
        "value": "{color.grey.400}"
      },
      "disabled": {
        "value": "{color.grey.400}"
      },
      "error": {
        "value": "{color.red.600}"
      },
      "success": {
        "value": "{color.green.600}"
      },
      "warning": {
        "value": "{color.yellow.600}"
      },
      "info": {
        "value": "{color.pink.600}"
      },
      "brand": {
        "primary": {
          "default": {
            "value": "{color.pink.300}"
          },
          "hover": {
            "value": "{color.pink.400}"
          },
          "selected": {
            "value": "{color.pink.600}"
          }
        }
      },
      "locked": {
        "default": {
          "value": "{color.grey.0}"
        },
        "brand": {
          "primary": {
            "value": "{color.pink.500}"
          },
          "secondary": {
            "value": "{color.purple.500}"
          }
        }
      }
    },
    "outline": {
      "default": {
        "value": "{color.grey.0}"
      },
      "error": {
        "value": "{color.red.400}"
      },
      "inverted": {
        "value": "{color.grey.500}"
      }
    },
    "icon": {
      "default": {
        "value": "{color.grey.0}"
      },
      "subtle": {
        "value": "{color.grey.200}"
      },
      "disabled": {
        "value": "{color.grey.200}"
      },
      "info": {
        "value": "{color.pink.300}"
      },
      "error": {
        "value": "{color.red.400}"
      },
      "success": {
        "value": "{color.green.400}"
      },
      "warning": {
        "value": "{color.yellow.300}"
      },
      "brand": {
        "primary": {
          "default": {
            "value": "{color.pink.300}"
          },
          "hover": {
            "value": "{color.pink.400}"
          }
        }
      },
      "inverted": {
        "value": "{color.grey.500}"
      }
    }
  },
  "separator": {
    "color": {
      "default": {
        "value": "{color.grey.300}"
      },
      "subtle": {
        "value": "{color.grey.400}"
      }
    }
  }
}
